{
  "title": "Loaded Lobster Rolls | DJ BBQ",
  "video_published_at": "2014-12-11T10:56:58Z",
  "start_at": null,
  "end_at": null,
  "video_id": "0GJlXPW_aq4",
  "published_at": "2017-06-24T05:51:50Z",
  "description": "(PP) Contains Product Placement. Hi Food Tubers! DJ BBQ has a winner of a recipe for your festive celebrations – succulent lobster tossed through a spiced lemony mayonnaise and stacked high on buttery brioche buns. Awesometacular! If you want to add some sparkle to your celebrations, make sure you give this one a go. For more tasty recipes like this check out www.jamieoliver.com/hellmanns\n\nLinks from the video:\nHow to Prep a Lobster | http://www.youtube.com/watch?v=c1pBosTOacA\nJamie's Beef Ribs and Slaw | http://goo.gl/xZdGAK\nMore foodtube videos | http://goo.gl/vyzskD\n\nDJ BBQ's Channel: http://goo.gl/l7onF9\n\nFor more nutrition info, click here: http://jamieol.com/D3JimM\n\nJamie Oliver's Food Tube | http://goo.gl/EdJ0vK\nSubscribe to Food Tube | http://goo.gl/v0tQr\nTwitter: https://twitter.com/JamiesFoodTube\nJamie's Recipes App | http://goo.gl/O7keA7\nTumblr: http://jamieoliverfoodtube.tumblr.com/\nFacebook | http://goo.gl/7R0xdh\nMore great recipes | http://www.jamieoliver.com\n\n#FOODTUBE\n\nx",
  "thumbnails": {
    "default": {
      "height": 90,
      "url": "https://i.ytimg.com/vi/0GJlXPW_aq4/default.jpg",
      "width": 120
    },
    "medium": {
      "height": 180,
      "url": "https://i.ytimg.com/vi/0GJlXPW_aq4/mqdefault.jpg",
      "width": 320
    },
    "high": {
      "height": 360,
      "url": "https://i.ytimg.com/vi/0GJlXPW_aq4/hqdefault.jpg",
      "width": 480
    },
    "standard": {
      "height": 480,
      "url": "https://i.ytimg.com/vi/0GJlXPW_aq4/sddefault.jpg",
      "width": 640
    },
    "maxres": {
      "height": 720,
      "url": "https://i.ytimg.com/vi/0GJlXPW_aq4/maxresdefault.jpg",
      "width": 1280
    }
  }
}