{
  "title": "Baked \"Fried\" Rice - Easy Fried Rice in the Oven - Food Wishes",
  "video_published_at": "2019-03-23T01:27:18Z",
  "start_at": null,
  "end_at": null,
  "video_id": "1q576aZQICU",
  "published_at": "2019-03-23T15:38:51Z",
  "description": "Learn how to make a Baked \"Fried\" Rice recipe! If you have a bunch of leftover rice, just use the classic method, but if you don’t, this oven method for making fried rice not only produces something very similar in taste, but the texture of your rice will come out perfect every time. Visit https://foodwishes.blogspot.com/2019/03/baked-fried-rice-once-cooked.html for the ingredients, more information, and many, many more video recipes. I really hope you enjoy this easy Baked \"Fried\" Rice recipe!\n\nYou can also find my content on Allrecipes: http://allrecipes.com/recipes/16791/everyday-cooking/special-collections/web-show-recipes/food-wishes/”",
  "thumbnails": {
    "default": {
      "height": 90,
      "url": "https://i.ytimg.com/vi/1q576aZQICU/default.jpg",
      "width": 120
    },
    "medium": {
      "height": 180,
      "url": "https://i.ytimg.com/vi/1q576aZQICU/mqdefault.jpg",
      "width": 320
    },
    "high": {
      "height": 360,
      "url": "https://i.ytimg.com/vi/1q576aZQICU/hqdefault.jpg",
      "width": 480
    },
    "standard": {
      "height": 480,
      "url": "https://i.ytimg.com/vi/1q576aZQICU/sddefault.jpg",
      "width": 640
    },
    "maxres": {
      "height": 720,
      "url": "https://i.ytimg.com/vi/1q576aZQICU/maxresdefault.jpg",
      "width": 1280
    }
  }
}