{
  "title": "Spanish Garlic Soup - Sopa de Ajo Recipe - Bread and Garlic Soup",
  "video_published_at": "2013-04-19T01:05:51Z",
  "start_at": null,
  "end_at": null,
  "video_id": "fixHiTWKRWA",
  "published_at": "2017-06-26T17:12:22Z",
  "description": "Learn how to make a Spanish Garlic Soup recipe! Go to http://foodwishes.blogspot.com/2013/04/celebrating-national-garlic-day-with.html for the ingredient amounts, more information, and many, many more video recipes! I hope you enjoy this easy Sopa de Ajo!",
  "thumbnails": {
    "default": {
      "height": 90,
      "url": "https://i.ytimg.com/vi/fixHiTWKRWA/default.jpg",
      "width": 120
    },
    "medium": {
      "height": 180,
      "url": "https://i.ytimg.com/vi/fixHiTWKRWA/mqdefault.jpg",
      "width": 320
    },
    "high": {
      "height": 360,
      "url": "https://i.ytimg.com/vi/fixHiTWKRWA/hqdefault.jpg",
      "width": 480
    },
    "standard": {
      "height": 480,
      "url": "https://i.ytimg.com/vi/fixHiTWKRWA/sddefault.jpg",
      "width": 640
    },
    "maxres": {
      "height": 720,
      "url": "https://i.ytimg.com/vi/fixHiTWKRWA/maxresdefault.jpg",
      "width": 1280
    }
  }
}