{
  "title": "Holiday Ravioli by Mario Batali's Grandma",
  "video_published_at": "2014-12-24T23:53:44Z",
  "start_at": null,
  "end_at": null,
  "video_id": "KaTdQ1peK70",
  "published_at": "2017-07-25T01:34:01Z",
  "description": "Mario Batali reminisces about his Grandma Leonetta and her legendary calves brain ravioli--then whips up a batch for his family.  Here's to holiday traditions!",
  "thumbnails": {
    "default": {
      "height": 90,
      "url": "https://i.ytimg.com/vi/KaTdQ1peK70/default.jpg",
      "width": 120
    },
    "medium": {
      "height": 180,
      "url": "https://i.ytimg.com/vi/KaTdQ1peK70/mqdefault.jpg",
      "width": 320
    },
    "high": {
      "height": 360,
      "url": "https://i.ytimg.com/vi/KaTdQ1peK70/hqdefault.jpg",
      "width": 480
    },
    "standard": {
      "height": 480,
      "url": "https://i.ytimg.com/vi/KaTdQ1peK70/sddefault.jpg",
      "width": 640
    },
    "maxres": {
      "height": 720,
      "url": "https://i.ytimg.com/vi/KaTdQ1peK70/maxresdefault.jpg",
      "width": 1280
    }
  }
}