{
  "title": "Korean Cheese Spicy Baby Back Ribs",
  "video_published_at": "2015-09-18T14:07:15Z",
  "start_at": null,
  "end_at": null,
  "video_id": "oBghN3zzCU8",
  "published_at": "2017-10-03T23:44:53Z",
  "description": "♥ Please Subscribe my channel for more delicious recipes!\nhttp://www.youtube.com/subscription_center?add_user=SeonkyoungLongest\n\n♥ Visit my website for written recipes and everyday meal! - http://www.SeonkyoungLongest.com\n\n♥ Like Asian at Home on Facebook for everyday update!-    http://www.facebook.com/seonkyounglongest\n\n♥ Follow me on Instagram!- http://instagram.com/SeonkyoungLongest\n\n♥ Follow me on Twitter! - http://twitter.com/Seonkyoung\n\n♥ Follow me on Pinterest -  http://pinterest.com/Seonkyoung\n\n\n\n♥ Step-by-Step Written Recipe:  http://seonkyounglongest.com/?p=4663\n\n♥ Cheese Baby Back Ribs Ingredients\nFor the Ribs\n1 Rack of baby back ribs (about 3lb.)\n7 Cups cold water\n10 Cloves garlic, crushed or 1 bulb of garlic cut into halves\n2 to 3Slices of fresh ginger (Oreo cookie size)\n1/2 Yellow or white onion, cut into quarter\n1/2 cup soju, sake(rice wine) or vodka\n1 Tbs. Black pepper corn\n2 Bay leaves\n4 Dried Thai chili, crushed or 1 Tbs. red pepper flakes\n3 Tbs. Soy sauce\n3 Tbs. Sugar\n\nFor the Sauce\n3 Tbs. Gochujang, Korean red pepper paste\n2 Tbs. Soy sauce\n2 Tbs. Mirin\n3 Tbs. Honey\n3 Tbs. Sambal, chili garlic sauce\n5 Cloves garlic\n2 Tbs. Korean sweet plum sauce, apricot preserve or apple jelly\n1/4 tsp. Black pepper\n\nFor the Cheese Mixture\n2 Cups Cheese\n3 Tbs. Sour cream, creama, heavy cream, cream cheese or milk\n\n\n❤️Music From AudioNetwork",
  "thumbnails": {
    "default": {
      "height": 90,
      "url": "https://i.ytimg.com/vi/oBghN3zzCU8/default.jpg",
      "width": 120
    },
    "medium": {
      "height": 180,
      "url": "https://i.ytimg.com/vi/oBghN3zzCU8/mqdefault.jpg",
      "width": 320
    },
    "high": {
      "height": 360,
      "url": "https://i.ytimg.com/vi/oBghN3zzCU8/hqdefault.jpg",
      "width": 480
    },
    "standard": {
      "height": 480,
      "url": "https://i.ytimg.com/vi/oBghN3zzCU8/sddefault.jpg",
      "width": 640
    },
    "maxres": {
      "height": 720,
      "url": "https://i.ytimg.com/vi/oBghN3zzCU8/maxresdefault.jpg",
      "width": 1280
    }
  }
}