{
  "title": "Homestyle Japanese Omurice | オムライス | Fried Rice Friday #4",
  "video_published_at": "2019-02-28T21:10:52Z",
  "start_at": null,
  "end_at": null,
  "video_id": "obwkhqu2-mc",
  "published_at": "2019-09-13T02:09:05Z",
  "description": "Omurice is one of the most popular Japanese home-cooked dishes. This fourth (and final - for now) instalment of Fried Rice Fridays is a simple fried rice known as “chicken rice” covered in a soft-set omelette and demi-glace sauce. There are three main styles of preparing the omelette for the omurice, and this is the most popular one.\n\nFull Recipe: http://adamliaw.com/recipe/homestyle-omurice/\nMore Recipes on Instagram: https://www.instagram.com/adamliaw/",
  "thumbnails": {
    "default": {
      "height": 90,
      "url": "https://i.ytimg.com/vi/obwkhqu2-mc/default.jpg",
      "width": 120
    },
    "medium": {
      "height": 180,
      "url": "https://i.ytimg.com/vi/obwkhqu2-mc/mqdefault.jpg",
      "width": 320
    },
    "high": {
      "height": 360,
      "url": "https://i.ytimg.com/vi/obwkhqu2-mc/hqdefault.jpg",
      "width": 480
    },
    "standard": {
      "height": 480,
      "url": "https://i.ytimg.com/vi/obwkhqu2-mc/sddefault.jpg",
      "width": 640
    },
    "maxres": {
      "height": 720,
      "url": "https://i.ytimg.com/vi/obwkhqu2-mc/maxresdefault.jpg",
      "width": 1280
    }
  }
}