{
  "title": "How To Make Okonomiyaki (Recipe) お好み焼きの作り方（レシピ）",
  "video_published_at": "2016-07-09T04:43:58Z",
  "start_at": null,
  "end_at": null,
  "video_id": "Y33iFBt1_PA",
  "published_at": "2018-05-29T04:19:38Z",
  "description": "Savory Japanese pancake made of batter and cabbage topped with okonomi sauce, mayo, katsuobushi, and aonori.  Originated from Osaka, Japan.\n\n★ FOLLOW JUST ONE COOKBOOK ★ \n📺 Please SUBSCRIBE :: http://bit.ly/JOCchannel\n🌎 My Blog :: http://www.justonecookbook.com\n📖 My Facebook :: http://facebook.com/justonecookbook\n🐤 My Twitter :: http://twitter.com/justonecookbook\n📷 My Instagram :: http://instagram.com/justonecookbook\n\nPRINT RECIPE ▼\n\nhttp://bit.ly/OkonomiyakiRecipe\n\nServes: 4\n\nIngredients:\n\n1 cup (120 g) all-purpose flour\n¼ tsp. salt\n¼ tsp. sugar\n¼ tsp. baking powder\n2-3 inch (5-8 cm) Nagaimo/Yamaimo\n¾ cup (180 ml) dashi, or ¾ cup water with 1 tsp. dashi powder\n1 large cabbage head (8-9 cups, 1.6 lb., 740 g)\n½ lb. (227 g) sliced pork belly\n4 large eggs\n½ cup (8 Tbsp.) tempura scraps (Tenkasu/Agedama)\n¼ cup (4 Tbsp.) pickled red ginger (Kizami Beni Shoga)\nVegetable oil\n\nOkonomiyaki Sauce\n\n1 ½ Tbsp. sugar\n2 Tbsp. oyster sauce\n4 Tbsp. ketchup\n3 ½ Tbsp. Worcestershire sauce\n\nToppings\n\nOkonomiyaki sauce (or homemade recipe)\nJapanese mayonnaise\nDried bonito flakes (Katsuobushi)\nDried green seaweed powder (Aonori)\nGreen onions/scallions\n\n\nInstructions with step-by-step pics▼\n\nhttp://bit.ly/OkonomiyakiRecipe\n\n\n★ INGREDIENTS & COOKING EQUIPMENT ★\n\nCUTTING BOARD :: http://www.cuttingboard.com\nWHISK :: http://amzn.to/1RyWQKY\nDASHI POWDER :: http://amzn.to/29tEwrv\nMINI SPATULA :: http://amzn.to/29tEwHZ\nKNIFE :: http://amzn.to/1RyWLHg\nTENKASU :: http://amzn.to/29pqkwk\nPICKLED RED GINGER :: http://amzn.to/29Wjpwj\nFRYING PAN :: http://amzn.to/1SiMTp4\n2 SPATULAS :: http://amzn.to/1SJuZxe\nSILICONE BRUSH :: http://amzn.to/29uf6sh\nOKONOMI SAUCE :: http://amzn.to/29WijRp\nJAPANESE MAYO :: http://amzn.to/29pqkfM\nDRIED BONITO FLAKES :: http://amzn.to/29Wj5h2\nDRIED GREEN SEAWEED POWDER :: http://amzn.to/29xp4uD\n\n\n★ MUSIC ★ \n\nMusic courtesy of Audio Network  \n\n♫ \"Happy Daze 2\" :: http://bit.ly/29nveyB\n♫ \"Sun Flower\" :: http://bit.ly/29ESJ4q\n♫ \"Nu Morning\" :: http://bit.ly/29ES96R\n\n★ VIDEO EQUIPMENT ★\n\nCAMERAS:: http://amzn.to/1QxqBLN\nLENS :: http://amzn.to/21gmQ8D & http://amzn.to/1R9psKm\nVIDEO MIC :: http://amzn.to/1Tmi58m\nTRIPODS :: http://amzn.to/1HUn1Xu\nLIGHTS :: http://amzn.to/1I84kEk\nSOFTWARE :: Adobe Premiere",
  "thumbnails": {
    "default": {
      "height": 90,
      "url": "https://i.ytimg.com/vi/Y33iFBt1_PA/default.jpg",
      "width": 120
    },
    "medium": {
      "height": 180,
      "url": "https://i.ytimg.com/vi/Y33iFBt1_PA/mqdefault.jpg",
      "width": 320
    },
    "high": {
      "height": 360,
      "url": "https://i.ytimg.com/vi/Y33iFBt1_PA/hqdefault.jpg",
      "width": 480
    },
    "standard": {
      "height": 480,
      "url": "https://i.ytimg.com/vi/Y33iFBt1_PA/sddefault.jpg",
      "width": 640
    },
    "maxres": {
      "height": 720,
      "url": "https://i.ytimg.com/vi/Y33iFBt1_PA/maxresdefault.jpg",
      "width": 1280
    }
  }
}